{"nodes": [{"id": "d_iia_serverv2_iia_server_iia_merge_release0324_frontend_test_src_components_buttoncontainer_jsx", "label": "ButtonContainer.jsx", "file_type": "code", "source_file": "D:\\IIA\\ServerV2\\IIA_Server\\IIA_Merge_Release0324\\Frontend-test\\src\\components\\ButtonContainer.jsx", "source_location": "L1"}, {"id": "components_buttoncontainer_buttoncontainer", "label": "ButtonContainer()", "file_type": "code", "source_file": "D:\\IIA\\ServerV2\\IIA_Server\\IIA_Merge_Release0324\\Frontend-test\\src\\components\\ButtonContainer.jsx", "source_location": "L13"}], "edges": [{"source": "d_iia_serverv2_iia_server_iia_merge_release0324_frontend_test_src_components_buttoncontainer_jsx", "target": "antd", "relation": "imports_from", "context": "import", "confidence": "EXTRACTED", "source_file": "D:\\IIA\\ServerV2\\IIA_Server\\IIA_Merge_Release0324\\Frontend-test\\src\\components\\ButtonContainer.jsx", "source_location": "L1", "weight": 1.0}, {"source": "d_iia_serverv2_iia_server_iia_merge_release0324_frontend_test_src_components_buttoncontainer_jsx", "target": "react", "relation": "imports_from", "context": "import", "confidence": "EXTRACTED", "source_file": "D:\\IIA\\ServerV2\\IIA_Server\\IIA_Merge_Release0324\\Frontend-test\\src\\components\\ButtonContainer.jsx", "source_location": "L3", "weight": 1.0}, {"source": "d_iia_serverv2_iia_server_iia_merge_release0324_frontend_test_src_components_buttoncontainer_jsx", "target": "icons", "relation": "imports_from", "context": "import", "confidence": "EXTRACTED", "source_file": "D:\\IIA\\ServerV2\\IIA_Server\\IIA_Merge_Release0324\\Frontend-test\\src\\components\\ButtonContainer.jsx", "source_location": "L4", "weight": 1.0}, {"source": "d_iia_serverv2_iia_server_iia_merge_release0324_frontend_test_src_components_buttoncontainer_jsx", "target": "react_router_dom", "relation": "imports_from", "context": "import", "confidence": "EXTRACTED", "source_file": "D:\\IIA\\ServerV2\\IIA_Server\\IIA_Merge_Release0324\\Frontend-test\\src\\components\\ButtonContainer.jsx", "source_location": "L11", "weight": 1.0}, {"source": "d_iia_serverv2_iia_server_iia_merge_release0324_frontend_test_src_components_buttoncontainer_jsx", "target": "components_buttoncontainer_buttoncontainer", "relation": "contains", "confidence": "EXTRACTED", "source_file": "D:\\IIA\\ServerV2\\IIA_Server\\IIA_Merge_Release0324\\Frontend-test\\src\\components\\ButtonContainer.jsx", "source_location": "L13", "weight": 1.0}], "raw_calls": [{"caller_nid": "components_buttoncontainer_buttoncontainer", "callee": "useState", "is_member_call": false, "source_file": "D:\\IIA\\ServerV2\\IIA_Server\\IIA_Merge_Release0324\\Frontend-test\\src\\components\\ButtonContainer.jsx", "source_location": "L27"}, {"caller_nid": "components_buttoncontainer_buttoncontainer", "callee": "useNavigate", "is_member_call": false, "source_file": "D:\\IIA\\ServerV2\\IIA_Server\\IIA_Merge_Release0324\\Frontend-test\\src\\components\\ButtonContainer.jsx", "source_location": "L28"}, {"caller_nid": "components_buttoncontainer_buttoncontainer", "callee": "useLocation", "is_member_call": false, "source_file": "D:\\IIA\\ServerV2\\IIA_Server\\IIA_Merge_Release0324\\Frontend-test\\src\\components\\ButtonContainer.jsx", "source_location": "L29"}]}